pylangdetect/__init__.py
pylangdetect/core.py
pylangdetect-0.1.0.dist-info/METADATA
pylangdetect-0.1.0.dist-info/WHEEL
pylangdetect-0.1.0.dist-info/top_level.txt
pylangdetect-0.1.0.dist-info/RECORD
